aiproxy/__init__.py
aiproxy/__main__.py
aiproxy/accesslog.py
aiproxy/anthropic_claude.py
aiproxy/azurequeueclient.py
aiproxy/bedrock_claude.py
aiproxy/chatgpt.py
aiproxy/gemini.py
aiproxy/httpx_proxy.py
aiproxy/proxy.py
aiproxy/queueclient.py
aiproxy_python-0.4.4.dist-info/LICENSE
aiproxy_python-0.4.4.dist-info/METADATA
aiproxy_python-0.4.4.dist-info/WHEEL
aiproxy_python-0.4.4.dist-info/top_level.txt
aiproxy_python-0.4.4.dist-info/RECORD
