Metadata-Version: 2.1
Name: aiproxy-python
Version: 0.4.4
Summary: 🦉AIProxy is a reverse proxy for ChatGPT API that provides monitoring, logging, and filtering requests and responses.
Home-page: https://github.com/uezo/aiproxy
Author: uezo
Author-email: uezo@uezo.net
Maintainer: uezo
Maintainer-email: uezo@uezo.net
License: Apache v2
Classifier: Programming Language :: Python :: 3
License-File: LICENSE
Requires-Dist: httpx ==0.27.0
Requires-Dist: fastapi ==0.103.2
Requires-Dist: uvicorn ==0.23.2
Requires-Dist: sse-starlette ==1.8.2
Requires-Dist: tiktoken ==0.5.1
Requires-Dist: SQLAlchemy ==2.0.23
